{
    
 "AppRedirect": {
    "status"     : false,
    "redirectURL": "https://play.google.com/store/apps/details?id=com.piupiuapps.coloringglitterunicorns"
  },
  
  
 "AdsController": {
   
    "README": "To run ads for each network, enter one of the following: 'admob' , 'applovin' , 'unity' ",
   
    "BannerNetwork"      : "applovin",
    "InterstitialNetwork": "applovin",
    "NativeNetwork"      : "applovin",
    "RewardNetwork"      : "applovin",
    
    "AdInterval"         : 1,
    
    "AdPlacement": {
        
      "AdMobBanner"          : "",
      "AdMobInterstitial"    : "",
      "AdMobNative"          : "",
      "AdMobReward"          : "",
     
      "ApplovinKey"          : "Ey33AenqTE14O6tdtv_gGzpDkuPThCbsc0SJf9H1Zw6fGrg34CBMapNm2IOqagfvnINqLIZuRZtQ98nKnPaFJ4",
      "ApplovinBanner"       : "cdd73c6d5fa58540",
      "ApplovinInterstitial" : "50213a922dd044df",
      "ApplovinNative"       : "8a46e16c8600e083",
      "ApplovinReward"       : "0eceac3939b43e24",
      
      "UnityGameID"           : "4076527",
      "UnityBanner"           : "BannerAd",
      "UnityInterstitialAd"   : "InterstitialAd",
      "UnityRewardAd"         : "rewardedVideo"
    }
  },
  

  "VPNSetting": {
      
    "ConnectionType": "off",
    
    "VpnUserName"   : "vpnbook",
    "VpnPassword"   : "huba7re",
    
    "BlockedCountry": "ca,uk,usa",
    
    "VpnFiles": [
     {
      "vpnName": "nz-aes",
      "vpnFile": "https://raw.githubusercontent.com/afortnitegenerator/jibekgari/refs/heads/main/vpnbook-ca149-tcp443.ovpn"
    },
{
      "vpnName": "au_australia",
      "vpnFile": "https://raw.githubusercontent.com/afortnitegenerator/jibekgari/refs/heads/main/vpnbook-ca149-tcp80.ovpn"
    },
{
      "vpnName": "aus-aes",
      "vpnFile": "https://raw.githubusercontent.com/afortnitegenerator/jibekgari/refs/heads/main/vpnbook-ca149-udp25000.ovpn"
    },
{
      "vpnName": "aus_perth",
      "vpnFile": "https://raw.githubusercontent.com/afortnitegenerator/jibekgari/refs/heads/main/vpnbook-ca149-udp53.ovpn"
    }
    ]
  }
}
